{
  "topic": "15_项目调度甘特图",
  "generated_at": "2026-02-01T23:17:41.618580",
  "total_images": 175,
  "images": [
    {
      "filename": "2305_17247v1_p1_img1.jpeg",
      "arxiv_id": "2305.17247v1",
      "title": "The Araucaria Project: Improving the cosmic distance scale",
      "authors": [
        "The Araucaria Project",
        ":",
        "G. Pietrzyński"
      ],
      "published": "2023-05-26",
      "arxiv_url": "http://arxiv.org/abs/2305.17247v1",
      "pdf_url": "https://arxiv.org/pdf/2305.17247v1",
      "page": 1,
      "image_index": 1,
      "file_size": 2347614,
      "format": "jpeg"
    },
    {
      "filename": "2305_17247v1_p3_img1.png",
      "arxiv_id": "2305.17247v1",
      "title": "The Araucaria Project: Improving the cosmic distance scale",
      "authors": [
        "The Araucaria Project",
        ":",
        "G. Pietrzyński"
      ],
      "published": "2023-05-26",
      "arxiv_url": "http://arxiv.org/abs/2305.17247v1",
      "pdf_url": "https://arxiv.org/pdf/2305.17247v1",
      "page": 3,
      "image_index": 1,
      "file_size": 22594,
      "format": "png"
    },
    {
      "filename": "2305_17247v1_p3_img2.jpeg",
      "arxiv_id": "2305.17247v1",
      "title": "The Araucaria Project: Improving the cosmic distance scale",
      "authors": [
        "The Araucaria Project",
        ":",
        "G. Pietrzyński"
      ],
      "published": "2023-05-26",
      "arxiv_url": "http://arxiv.org/abs/2305.17247v1",
      "pdf_url": "https://arxiv.org/pdf/2305.17247v1",
      "page": 3,
      "image_index": 2,
      "file_size": 21961,
      "format": "jpeg"
    },
    {
      "filename": "2305_17247v1_p7_img1.jpeg",
      "arxiv_id": "2305.17247v1",
      "title": "The Araucaria Project: Improving the cosmic distance scale",
      "authors": [
        "The Araucaria Project",
        ":",
        "G. Pietrzyński"
      ],
      "published": "2023-05-26",
      "arxiv_url": "http://arxiv.org/abs/2305.17247v1",
      "pdf_url": "https://arxiv.org/pdf/2305.17247v1",
      "page": 7,
      "image_index": 1,
      "file_size": 416853,
      "format": "jpeg"
    },
    {
      "filename": "2305_17247v1_p8_img1.jpeg",
      "arxiv_id": "2305.17247v1",
      "title": "The Araucaria Project: Improving the cosmic distance scale",
      "authors": [
        "The Araucaria Project",
        ":",
        "G. Pietrzyński"
      ],
      "published": "2023-05-26",
      "arxiv_url": "http://arxiv.org/abs/2305.17247v1",
      "pdf_url": "https://arxiv.org/pdf/2305.17247v1",
      "page": 8,
      "image_index": 1,
      "file_size": 762446,
      "format": "jpeg"
    },
    {
      "filename": "2305_17247v1_p9_img1.jpeg",
      "arxiv_id": "2305.17247v1",
      "title": "The Araucaria Project: Improving the cosmic distance scale",
      "authors": [
        "The Araucaria Project",
        ":",
        "G. Pietrzyński"
      ],
      "published": "2023-05-26",
      "arxiv_url": "http://arxiv.org/abs/2305.17247v1",
      "pdf_url": "https://arxiv.org/pdf/2305.17247v1",
      "page": 9,
      "image_index": 1,
      "file_size": 1053309,
      "format": "jpeg"
    },
    {
      "filename": "2305_17247v1_p10_img1.jpeg",
      "arxiv_id": "2305.17247v1",
      "title": "The Araucaria Project: Improving the cosmic distance scale",
      "authors": [
        "The Araucaria Project",
        ":",
        "G. Pietrzyński"
      ],
      "published": "2023-05-26",
      "arxiv_url": "http://arxiv.org/abs/2305.17247v1",
      "pdf_url": "https://arxiv.org/pdf/2305.17247v1",
      "page": 10,
      "image_index": 1,
      "file_size": 1079125,
      "format": "jpeg"
    },
    {
      "filename": "2305_17247v1_p11_img1.jpeg",
      "arxiv_id": "2305.17247v1",
      "title": "The Araucaria Project: Improving the cosmic distance scale",
      "authors": [
        "The Araucaria Project",
        ":",
        "G. Pietrzyński"
      ],
      "published": "2023-05-26",
      "arxiv_url": "http://arxiv.org/abs/2305.17247v1",
      "pdf_url": "https://arxiv.org/pdf/2305.17247v1",
      "page": 11,
      "image_index": 1,
      "file_size": 957031,
      "format": "jpeg"
    },
    {
      "filename": "2305_17247v1_p13_img1.jpeg",
      "arxiv_id": "2305.17247v1",
      "title": "The Araucaria Project: Improving the cosmic distance scale",
      "authors": [
        "The Araucaria Project",
        ":",
        "G. Pietrzyński"
      ],
      "published": "2023-05-26",
      "arxiv_url": "http://arxiv.org/abs/2305.17247v1",
      "pdf_url": "https://arxiv.org/pdf/2305.17247v1",
      "page": 13,
      "image_index": 1,
      "file_size": 408686,
      "format": "jpeg"
    },
    {
      "filename": "2305_17247v1_p16_img1.jpeg",
      "arxiv_id": "2305.17247v1",
      "title": "The Araucaria Project: Improving the cosmic distance scale",
      "authors": [
        "The Araucaria Project",
        ":",
        "G. Pietrzyński"
      ],
      "published": "2023-05-26",
      "arxiv_url": "http://arxiv.org/abs/2305.17247v1",
      "pdf_url": "https://arxiv.org/pdf/2305.17247v1",
      "page": 16,
      "image_index": 1,
      "file_size": 882187,
      "format": "jpeg"
    },
    {
      "filename": "2305_17247v1_p18_img1.jpeg",
      "arxiv_id": "2305.17247v1",
      "title": "The Araucaria Project: Improving the cosmic distance scale",
      "authors": [
        "The Araucaria Project",
        ":",
        "G. Pietrzyński"
      ],
      "published": "2023-05-26",
      "arxiv_url": "http://arxiv.org/abs/2305.17247v1",
      "pdf_url": "https://arxiv.org/pdf/2305.17247v1",
      "page": 18,
      "image_index": 1,
      "file_size": 514242,
      "format": "jpeg"
    },
    {
      "filename": "2305_17247v1_p19_img1.png",
      "arxiv_id": "2305.17247v1",
      "title": "The Araucaria Project: Improving the cosmic distance scale",
      "authors": [
        "The Araucaria Project",
        ":",
        "G. Pietrzyński"
      ],
      "published": "2023-05-26",
      "arxiv_url": "http://arxiv.org/abs/2305.17247v1",
      "pdf_url": "https://arxiv.org/pdf/2305.17247v1",
      "page": 19,
      "image_index": 1,
      "file_size": 64312,
      "format": "png"
    },
    {
      "filename": "2305_17247v1_p21_img1.jpeg",
      "arxiv_id": "2305.17247v1",
      "title": "The Araucaria Project: Improving the cosmic distance scale",
      "authors": [
        "The Araucaria Project",
        ":",
        "G. Pietrzyński"
      ],
      "published": "2023-05-26",
      "arxiv_url": "http://arxiv.org/abs/2305.17247v1",
      "pdf_url": "https://arxiv.org/pdf/2305.17247v1",
      "page": 21,
      "image_index": 1,
      "file_size": 1986744,
      "format": "jpeg"
    },
    {
      "filename": "2305_17247v1_p22_img1.jpeg",
      "arxiv_id": "2305.17247v1",
      "title": "The Araucaria Project: Improving the cosmic distance scale",
      "authors": [
        "The Araucaria Project",
        ":",
        "G. Pietrzyński"
      ],
      "published": "2023-05-26",
      "arxiv_url": "http://arxiv.org/abs/2305.17247v1",
      "pdf_url": "https://arxiv.org/pdf/2305.17247v1",
      "page": 22,
      "image_index": 1,
      "file_size": 142981,
      "format": "jpeg"
    },
    {
      "filename": "2305_17247v1_p23_img1.jpeg",
      "arxiv_id": "2305.17247v1",
      "title": "The Araucaria Project: Improving the cosmic distance scale",
      "authors": [
        "The Araucaria Project",
        ":",
        "G. Pietrzyński"
      ],
      "published": "2023-05-26",
      "arxiv_url": "http://arxiv.org/abs/2305.17247v1",
      "pdf_url": "https://arxiv.org/pdf/2305.17247v1",
      "page": 23,
      "image_index": 1,
      "file_size": 58457,
      "format": "jpeg"
    },
    {
      "filename": "2305_17247v1_p25_img1.jpeg",
      "arxiv_id": "2305.17247v1",
      "title": "The Araucaria Project: Improving the cosmic distance scale",
      "authors": [
        "The Araucaria Project",
        ":",
        "G. Pietrzyński"
      ],
      "published": "2023-05-26",
      "arxiv_url": "http://arxiv.org/abs/2305.17247v1",
      "pdf_url": "https://arxiv.org/pdf/2305.17247v1",
      "page": 25,
      "image_index": 1,
      "file_size": 435193,
      "format": "jpeg"
    },
    {
      "filename": "2305_17247v1_p28_img1.png",
      "arxiv_id": "2305.17247v1",
      "title": "The Araucaria Project: Improving the cosmic distance scale",
      "authors": [
        "The Araucaria Project",
        ":",
        "G. Pietrzyński"
      ],
      "published": "2023-05-26",
      "arxiv_url": "http://arxiv.org/abs/2305.17247v1",
      "pdf_url": "https://arxiv.org/pdf/2305.17247v1",
      "page": 28,
      "image_index": 1,
      "file_size": 1415154,
      "format": "png"
    },
    {
      "filename": "2305_17247v1_p31_img1.png",
      "arxiv_id": "2305.17247v1",
      "title": "The Araucaria Project: Improving the cosmic distance scale",
      "authors": [
        "The Araucaria Project",
        ":",
        "G. Pietrzyński"
      ],
      "published": "2023-05-26",
      "arxiv_url": "http://arxiv.org/abs/2305.17247v1",
      "pdf_url": "https://arxiv.org/pdf/2305.17247v1",
      "page": 31,
      "image_index": 1,
      "file_size": 673517,
      "format": "png"
    },
    {
      "filename": "2305_17247v1_p31_img2.png",
      "arxiv_id": "2305.17247v1",
      "title": "The Araucaria Project: Improving the cosmic distance scale",
      "authors": [
        "The Araucaria Project",
        ":",
        "G. Pietrzyński"
      ],
      "published": "2023-05-26",
      "arxiv_url": "http://arxiv.org/abs/2305.17247v1",
      "pdf_url": "https://arxiv.org/pdf/2305.17247v1",
      "page": 31,
      "image_index": 2,
      "file_size": 131141,
      "format": "png"
    },
    {
      "filename": "2305_17247v1_p34_img1.png",
      "arxiv_id": "2305.17247v1",
      "title": "The Araucaria Project: Improving the cosmic distance scale",
      "authors": [
        "The Araucaria Project",
        ":",
        "G. Pietrzyński"
      ],
      "published": "2023-05-26",
      "arxiv_url": "http://arxiv.org/abs/2305.17247v1",
      "pdf_url": "https://arxiv.org/pdf/2305.17247v1",
      "page": 34,
      "image_index": 1,
      "file_size": 217168,
      "format": "png"
    },
    {
      "filename": "2305_17247v1_p37_img1.png",
      "arxiv_id": "2305.17247v1",
      "title": "The Araucaria Project: Improving the cosmic distance scale",
      "authors": [
        "The Araucaria Project",
        ":",
        "G. Pietrzyński"
      ],
      "published": "2023-05-26",
      "arxiv_url": "http://arxiv.org/abs/2305.17247v1",
      "pdf_url": "https://arxiv.org/pdf/2305.17247v1",
      "page": 37,
      "image_index": 1,
      "file_size": 68271,
      "format": "png"
    },
    {
      "filename": "2305_17247v1_p38_img1.png",
      "arxiv_id": "2305.17247v1",
      "title": "The Araucaria Project: Improving the cosmic distance scale",
      "authors": [
        "The Araucaria Project",
        ":",
        "G. Pietrzyński"
      ],
      "published": "2023-05-26",
      "arxiv_url": "http://arxiv.org/abs/2305.17247v1",
      "pdf_url": "https://arxiv.org/pdf/2305.17247v1",
      "page": 38,
      "image_index": 1,
      "file_size": 274898,
      "format": "png"
    },
    {
      "filename": "2305_17247v1_p40_img1.png",
      "arxiv_id": "2305.17247v1",
      "title": "The Araucaria Project: Improving the cosmic distance scale",
      "authors": [
        "The Araucaria Project",
        ":",
        "G. Pietrzyński"
      ],
      "published": "2023-05-26",
      "arxiv_url": "http://arxiv.org/abs/2305.17247v1",
      "pdf_url": "https://arxiv.org/pdf/2305.17247v1",
      "page": 40,
      "image_index": 1,
      "file_size": 232192,
      "format": "png"
    },
    {
      "filename": "2305_17247v1_p43_img1.png",
      "arxiv_id": "2305.17247v1",
      "title": "The Araucaria Project: Improving the cosmic distance scale",
      "authors": [
        "The Araucaria Project",
        ":",
        "G. Pietrzyński"
      ],
      "published": "2023-05-26",
      "arxiv_url": "http://arxiv.org/abs/2305.17247v1",
      "pdf_url": "https://arxiv.org/pdf/2305.17247v1",
      "page": 43,
      "image_index": 1,
      "file_size": 452024,
      "format": "png"
    },
    {
      "filename": "2305_17247v1_p44_img1.png",
      "arxiv_id": "2305.17247v1",
      "title": "The Araucaria Project: Improving the cosmic distance scale",
      "authors": [
        "The Araucaria Project",
        ":",
        "G. Pietrzyński"
      ],
      "published": "2023-05-26",
      "arxiv_url": "http://arxiv.org/abs/2305.17247v1",
      "pdf_url": "https://arxiv.org/pdf/2305.17247v1",
      "page": 44,
      "image_index": 1,
      "file_size": 327215,
      "format": "png"
    },
    {
      "filename": "2305_17247v1_p46_img1.png",
      "arxiv_id": "2305.17247v1",
      "title": "The Araucaria Project: Improving the cosmic distance scale",
      "authors": [
        "The Araucaria Project",
        ":",
        "G. Pietrzyński"
      ],
      "published": "2023-05-26",
      "arxiv_url": "http://arxiv.org/abs/2305.17247v1",
      "pdf_url": "https://arxiv.org/pdf/2305.17247v1",
      "page": 46,
      "image_index": 1,
      "file_size": 190734,
      "format": "png"
    },
    {
      "filename": "2305_17247v1_p47_img1.png",
      "arxiv_id": "2305.17247v1",
      "title": "The Araucaria Project: Improving the cosmic distance scale",
      "authors": [
        "The Araucaria Project",
        ":",
        "G. Pietrzyński"
      ],
      "published": "2023-05-26",
      "arxiv_url": "http://arxiv.org/abs/2305.17247v1",
      "pdf_url": "https://arxiv.org/pdf/2305.17247v1",
      "page": 47,
      "image_index": 1,
      "file_size": 245061,
      "format": "png"
    },
    {
      "filename": "2305_17247v1_p49_img1.png",
      "arxiv_id": "2305.17247v1",
      "title": "The Araucaria Project: Improving the cosmic distance scale",
      "authors": [
        "The Araucaria Project",
        ":",
        "G. Pietrzyński"
      ],
      "published": "2023-05-26",
      "arxiv_url": "http://arxiv.org/abs/2305.17247v1",
      "pdf_url": "https://arxiv.org/pdf/2305.17247v1",
      "page": 49,
      "image_index": 1,
      "file_size": 77304,
      "format": "png"
    },
    {
      "filename": "2305_17247v1_p49_img2.jpeg",
      "arxiv_id": "2305.17247v1",
      "title": "The Araucaria Project: Improving the cosmic distance scale",
      "authors": [
        "The Araucaria Project",
        ":",
        "G. Pietrzyński"
      ],
      "published": "2023-05-26",
      "arxiv_url": "http://arxiv.org/abs/2305.17247v1",
      "pdf_url": "https://arxiv.org/pdf/2305.17247v1",
      "page": 49,
      "image_index": 2,
      "file_size": 212833,
      "format": "jpeg"
    },
    {
      "filename": "2305_17247v1_p50_img1.jpeg",
      "arxiv_id": "2305.17247v1",
      "title": "The Araucaria Project: Improving the cosmic distance scale",
      "authors": [
        "The Araucaria Project",
        ":",
        "G. Pietrzyński"
      ],
      "published": "2023-05-26",
      "arxiv_url": "http://arxiv.org/abs/2305.17247v1",
      "pdf_url": "https://arxiv.org/pdf/2305.17247v1",
      "page": 50,
      "image_index": 1,
      "file_size": 957469,
      "format": "jpeg"
    },
    {
      "filename": "2305_17247v1_p52_img1.jpeg",
      "arxiv_id": "2305.17247v1",
      "title": "The Araucaria Project: Improving the cosmic distance scale",
      "authors": [
        "The Araucaria Project",
        ":",
        "G. Pietrzyński"
      ],
      "published": "2023-05-26",
      "arxiv_url": "http://arxiv.org/abs/2305.17247v1",
      "pdf_url": "https://arxiv.org/pdf/2305.17247v1",
      "page": 52,
      "image_index": 1,
      "file_size": 297557,
      "format": "jpeg"
    },
    {
      "filename": "2305_17247v1_p53_img1.jpeg",
      "arxiv_id": "2305.17247v1",
      "title": "The Araucaria Project: Improving the cosmic distance scale",
      "authors": [
        "The Araucaria Project",
        ":",
        "G. Pietrzyński"
      ],
      "published": "2023-05-26",
      "arxiv_url": "http://arxiv.org/abs/2305.17247v1",
      "pdf_url": "https://arxiv.org/pdf/2305.17247v1",
      "page": 53,
      "image_index": 1,
      "file_size": 272222,
      "format": "jpeg"
    },
    {
      "filename": "2305_17247v1_p55_img1.png",
      "arxiv_id": "2305.17247v1",
      "title": "The Araucaria Project: Improving the cosmic distance scale",
      "authors": [
        "The Araucaria Project",
        ":",
        "G. Pietrzyński"
      ],
      "published": "2023-05-26",
      "arxiv_url": "http://arxiv.org/abs/2305.17247v1",
      "pdf_url": "https://arxiv.org/pdf/2305.17247v1",
      "page": 55,
      "image_index": 1,
      "file_size": 558498,
      "format": "png"
    },
    {
      "filename": "2305_17247v1_p56_img1.jpeg",
      "arxiv_id": "2305.17247v1",
      "title": "The Araucaria Project: Improving the cosmic distance scale",
      "authors": [
        "The Araucaria Project",
        ":",
        "G. Pietrzyński"
      ],
      "published": "2023-05-26",
      "arxiv_url": "http://arxiv.org/abs/2305.17247v1",
      "pdf_url": "https://arxiv.org/pdf/2305.17247v1",
      "page": 56,
      "image_index": 1,
      "file_size": 316757,
      "format": "jpeg"
    },
    {
      "filename": "2305_17247v1_p58_img1.jpeg",
      "arxiv_id": "2305.17247v1",
      "title": "The Araucaria Project: Improving the cosmic distance scale",
      "authors": [
        "The Araucaria Project",
        ":",
        "G. Pietrzyński"
      ],
      "published": "2023-05-26",
      "arxiv_url": "http://arxiv.org/abs/2305.17247v1",
      "pdf_url": "https://arxiv.org/pdf/2305.17247v1",
      "page": 58,
      "image_index": 1,
      "file_size": 282315,
      "format": "jpeg"
    },
    {
      "filename": "2305_17247v1_p59_img1.jpeg",
      "arxiv_id": "2305.17247v1",
      "title": "The Araucaria Project: Improving the cosmic distance scale",
      "authors": [
        "The Araucaria Project",
        ":",
        "G. Pietrzyński"
      ],
      "published": "2023-05-26",
      "arxiv_url": "http://arxiv.org/abs/2305.17247v1",
      "pdf_url": "https://arxiv.org/pdf/2305.17247v1",
      "page": 59,
      "image_index": 1,
      "file_size": 385429,
      "format": "jpeg"
    },
    {
      "filename": "2305_17247v1_p59_img2.jpeg",
      "arxiv_id": "2305.17247v1",
      "title": "The Araucaria Project: Improving the cosmic distance scale",
      "authors": [
        "The Araucaria Project",
        ":",
        "G. Pietrzyński"
      ],
      "published": "2023-05-26",
      "arxiv_url": "http://arxiv.org/abs/2305.17247v1",
      "pdf_url": "https://arxiv.org/pdf/2305.17247v1",
      "page": 59,
      "image_index": 2,
      "file_size": 63983,
      "format": "jpeg"
    },
    {
      "filename": "2305_17247v1_p61_img1.png",
      "arxiv_id": "2305.17247v1",
      "title": "The Araucaria Project: Improving the cosmic distance scale",
      "authors": [
        "The Araucaria Project",
        ":",
        "G. Pietrzyński"
      ],
      "published": "2023-05-26",
      "arxiv_url": "http://arxiv.org/abs/2305.17247v1",
      "pdf_url": "https://arxiv.org/pdf/2305.17247v1",
      "page": 61,
      "image_index": 1,
      "file_size": 106519,
      "format": "png"
    },
    {
      "filename": "2305_17247v1_p62_img1.png",
      "arxiv_id": "2305.17247v1",
      "title": "The Araucaria Project: Improving the cosmic distance scale",
      "authors": [
        "The Araucaria Project",
        ":",
        "G. Pietrzyński"
      ],
      "published": "2023-05-26",
      "arxiv_url": "http://arxiv.org/abs/2305.17247v1",
      "pdf_url": "https://arxiv.org/pdf/2305.17247v1",
      "page": 62,
      "image_index": 1,
      "file_size": 161255,
      "format": "png"
    },
    {
      "filename": "2305_17247v1_p64_img1.png",
      "arxiv_id": "2305.17247v1",
      "title": "The Araucaria Project: Improving the cosmic distance scale",
      "authors": [
        "The Araucaria Project",
        ":",
        "G. Pietrzyński"
      ],
      "published": "2023-05-26",
      "arxiv_url": "http://arxiv.org/abs/2305.17247v1",
      "pdf_url": "https://arxiv.org/pdf/2305.17247v1",
      "page": 64,
      "image_index": 1,
      "file_size": 1023919,
      "format": "png"
    },
    {
      "filename": "2305_17247v1_p67_img1.png",
      "arxiv_id": "2305.17247v1",
      "title": "The Araucaria Project: Improving the cosmic distance scale",
      "authors": [
        "The Araucaria Project",
        ":",
        "G. Pietrzyński"
      ],
      "published": "2023-05-26",
      "arxiv_url": "http://arxiv.org/abs/2305.17247v1",
      "pdf_url": "https://arxiv.org/pdf/2305.17247v1",
      "page": 67,
      "image_index": 1,
      "file_size": 123084,
      "format": "png"
    },
    {
      "filename": "2305_17247v1_p68_img1.png",
      "arxiv_id": "2305.17247v1",
      "title": "The Araucaria Project: Improving the cosmic distance scale",
      "authors": [
        "The Araucaria Project",
        ":",
        "G. Pietrzyński"
      ],
      "published": "2023-05-26",
      "arxiv_url": "http://arxiv.org/abs/2305.17247v1",
      "pdf_url": "https://arxiv.org/pdf/2305.17247v1",
      "page": 68,
      "image_index": 1,
      "file_size": 123415,
      "format": "png"
    },
    {
      "filename": "2305_17247v1_p68_img2.jpeg",
      "arxiv_id": "2305.17247v1",
      "title": "The Araucaria Project: Improving the cosmic distance scale",
      "authors": [
        "The Araucaria Project",
        ":",
        "G. Pietrzyński"
      ],
      "published": "2023-05-26",
      "arxiv_url": "http://arxiv.org/abs/2305.17247v1",
      "pdf_url": "https://arxiv.org/pdf/2305.17247v1",
      "page": 68,
      "image_index": 2,
      "file_size": 143750,
      "format": "jpeg"
    },
    {
      "filename": "2305_17247v1_p71_img1.jpeg",
      "arxiv_id": "2305.17247v1",
      "title": "The Araucaria Project: Improving the cosmic distance scale",
      "authors": [
        "The Araucaria Project",
        ":",
        "G. Pietrzyński"
      ],
      "published": "2023-05-26",
      "arxiv_url": "http://arxiv.org/abs/2305.17247v1",
      "pdf_url": "https://arxiv.org/pdf/2305.17247v1",
      "page": 71,
      "image_index": 1,
      "file_size": 378325,
      "format": "jpeg"
    },
    {
      "filename": "2305_17247v1_p74_img1.jpeg",
      "arxiv_id": "2305.17247v1",
      "title": "The Araucaria Project: Improving the cosmic distance scale",
      "authors": [
        "The Araucaria Project",
        ":",
        "G. Pietrzyński"
      ],
      "published": "2023-05-26",
      "arxiv_url": "http://arxiv.org/abs/2305.17247v1",
      "pdf_url": "https://arxiv.org/pdf/2305.17247v1",
      "page": 74,
      "image_index": 1,
      "file_size": 229595,
      "format": "jpeg"
    },
    {
      "filename": "2305_17247v1_p75_img1.jpeg",
      "arxiv_id": "2305.17247v1",
      "title": "The Araucaria Project: Improving the cosmic distance scale",
      "authors": [
        "The Araucaria Project",
        ":",
        "G. Pietrzyński"
      ],
      "published": "2023-05-26",
      "arxiv_url": "http://arxiv.org/abs/2305.17247v1",
      "pdf_url": "https://arxiv.org/pdf/2305.17247v1",
      "page": 75,
      "image_index": 1,
      "file_size": 118293,
      "format": "jpeg"
    },
    {
      "filename": "2305_17247v1_p77_img1.jpeg",
      "arxiv_id": "2305.17247v1",
      "title": "The Araucaria Project: Improving the cosmic distance scale",
      "authors": [
        "The Araucaria Project",
        ":",
        "G. Pietrzyński"
      ],
      "published": "2023-05-26",
      "arxiv_url": "http://arxiv.org/abs/2305.17247v1",
      "pdf_url": "https://arxiv.org/pdf/2305.17247v1",
      "page": 77,
      "image_index": 1,
      "file_size": 221231,
      "format": "jpeg"
    },
    {
      "filename": "2305_17247v1_p78_img1.png",
      "arxiv_id": "2305.17247v1",
      "title": "The Araucaria Project: Improving the cosmic distance scale",
      "authors": [
        "The Araucaria Project",
        ":",
        "G. Pietrzyński"
      ],
      "published": "2023-05-26",
      "arxiv_url": "http://arxiv.org/abs/2305.17247v1",
      "pdf_url": "https://arxiv.org/pdf/2305.17247v1",
      "page": 78,
      "image_index": 1,
      "file_size": 322247,
      "format": "png"
    },
    {
      "filename": "2305_17247v1_p83_img1.jpeg",
      "arxiv_id": "2305.17247v1",
      "title": "The Araucaria Project: Improving the cosmic distance scale",
      "authors": [
        "The Araucaria Project",
        ":",
        "G. Pietrzyński"
      ],
      "published": "2023-05-26",
      "arxiv_url": "http://arxiv.org/abs/2305.17247v1",
      "pdf_url": "https://arxiv.org/pdf/2305.17247v1",
      "page": 83,
      "image_index": 1,
      "file_size": 434963,
      "format": "jpeg"
    },
    {
      "filename": "2305_17247v1_p84_img1.png",
      "arxiv_id": "2305.17247v1",
      "title": "The Araucaria Project: Improving the cosmic distance scale",
      "authors": [
        "The Araucaria Project",
        ":",
        "G. Pietrzyński"
      ],
      "published": "2023-05-26",
      "arxiv_url": "http://arxiv.org/abs/2305.17247v1",
      "pdf_url": "https://arxiv.org/pdf/2305.17247v1",
      "page": 84,
      "image_index": 1,
      "file_size": 233101,
      "format": "png"
    },
    {
      "filename": "2305_17247v1_p86_img1.jpeg",
      "arxiv_id": "2305.17247v1",
      "title": "The Araucaria Project: Improving the cosmic distance scale",
      "authors": [
        "The Araucaria Project",
        ":",
        "G. Pietrzyński"
      ],
      "published": "2023-05-26",
      "arxiv_url": "http://arxiv.org/abs/2305.17247v1",
      "pdf_url": "https://arxiv.org/pdf/2305.17247v1",
      "page": 86,
      "image_index": 1,
      "file_size": 537177,
      "format": "jpeg"
    },
    {
      "filename": "2305_17247v1_p87_img1.png",
      "arxiv_id": "2305.17247v1",
      "title": "The Araucaria Project: Improving the cosmic distance scale",
      "authors": [
        "The Araucaria Project",
        ":",
        "G. Pietrzyński"
      ],
      "published": "2023-05-26",
      "arxiv_url": "http://arxiv.org/abs/2305.17247v1",
      "pdf_url": "https://arxiv.org/pdf/2305.17247v1",
      "page": 87,
      "image_index": 1,
      "file_size": 367570,
      "format": "png"
    },
    {
      "filename": "2305_17247v1_p89_img1.png",
      "arxiv_id": "2305.17247v1",
      "title": "The Araucaria Project: Improving the cosmic distance scale",
      "authors": [
        "The Araucaria Project",
        ":",
        "G. Pietrzyński"
      ],
      "published": "2023-05-26",
      "arxiv_url": "http://arxiv.org/abs/2305.17247v1",
      "pdf_url": "https://arxiv.org/pdf/2305.17247v1",
      "page": 89,
      "image_index": 1,
      "file_size": 546822,
      "format": "png"
    },
    {
      "filename": "2305_17247v1_p89_img2.png",
      "arxiv_id": "2305.17247v1",
      "title": "The Araucaria Project: Improving the cosmic distance scale",
      "authors": [
        "The Araucaria Project",
        ":",
        "G. Pietrzyński"
      ],
      "published": "2023-05-26",
      "arxiv_url": "http://arxiv.org/abs/2305.17247v1",
      "pdf_url": "https://arxiv.org/pdf/2305.17247v1",
      "page": 89,
      "image_index": 2,
      "file_size": 582475,
      "format": "png"
    },
    {
      "filename": "2305_17247v1_p92_img1.png",
      "arxiv_id": "2305.17247v1",
      "title": "The Araucaria Project: Improving the cosmic distance scale",
      "authors": [
        "The Araucaria Project",
        ":",
        "G. Pietrzyński"
      ],
      "published": "2023-05-26",
      "arxiv_url": "http://arxiv.org/abs/2305.17247v1",
      "pdf_url": "https://arxiv.org/pdf/2305.17247v1",
      "page": 92,
      "image_index": 1,
      "file_size": 393035,
      "format": "png"
    },
    {
      "filename": "2305_17247v1_p96_img1.jpeg",
      "arxiv_id": "2305.17247v1",
      "title": "The Araucaria Project: Improving the cosmic distance scale",
      "authors": [
        "The Araucaria Project",
        ":",
        "G. Pietrzyński"
      ],
      "published": "2023-05-26",
      "arxiv_url": "http://arxiv.org/abs/2305.17247v1",
      "pdf_url": "https://arxiv.org/pdf/2305.17247v1",
      "page": 96,
      "image_index": 1,
      "file_size": 701250,
      "format": "jpeg"
    },
    {
      "filename": "2305_17247v1_p99_img1.jpeg",
      "arxiv_id": "2305.17247v1",
      "title": "The Araucaria Project: Improving the cosmic distance scale",
      "authors": [
        "The Araucaria Project",
        ":",
        "G. Pietrzyński"
      ],
      "published": "2023-05-26",
      "arxiv_url": "http://arxiv.org/abs/2305.17247v1",
      "pdf_url": "https://arxiv.org/pdf/2305.17247v1",
      "page": 99,
      "image_index": 1,
      "file_size": 361905,
      "format": "jpeg"
    },
    {
      "filename": "2305_17247v1_p100_img1.jpeg",
      "arxiv_id": "2305.17247v1",
      "title": "The Araucaria Project: Improving the cosmic distance scale",
      "authors": [
        "The Araucaria Project",
        ":",
        "G. Pietrzyński"
      ],
      "published": "2023-05-26",
      "arxiv_url": "http://arxiv.org/abs/2305.17247v1",
      "pdf_url": "https://arxiv.org/pdf/2305.17247v1",
      "page": 100,
      "image_index": 1,
      "file_size": 384828,
      "format": "jpeg"
    },
    {
      "filename": "2305_17247v1_p100_img2.jpeg",
      "arxiv_id": "2305.17247v1",
      "title": "The Araucaria Project: Improving the cosmic distance scale",
      "authors": [
        "The Araucaria Project",
        ":",
        "G. Pietrzyński"
      ],
      "published": "2023-05-26",
      "arxiv_url": "http://arxiv.org/abs/2305.17247v1",
      "pdf_url": "https://arxiv.org/pdf/2305.17247v1",
      "page": 100,
      "image_index": 2,
      "file_size": 283946,
      "format": "jpeg"
    },
    {
      "filename": "2305_17247v1_p101_img1.jpeg",
      "arxiv_id": "2305.17247v1",
      "title": "The Araucaria Project: Improving the cosmic distance scale",
      "authors": [
        "The Araucaria Project",
        ":",
        "G. Pietrzyński"
      ],
      "published": "2023-05-26",
      "arxiv_url": "http://arxiv.org/abs/2305.17247v1",
      "pdf_url": "https://arxiv.org/pdf/2305.17247v1",
      "page": 101,
      "image_index": 1,
      "file_size": 436849,
      "format": "jpeg"
    },
    {
      "filename": "2305_17247v1_p102_img1.jpeg",
      "arxiv_id": "2305.17247v1",
      "title": "The Araucaria Project: Improving the cosmic distance scale",
      "authors": [
        "The Araucaria Project",
        ":",
        "G. Pietrzyński"
      ],
      "published": "2023-05-26",
      "arxiv_url": "http://arxiv.org/abs/2305.17247v1",
      "pdf_url": "https://arxiv.org/pdf/2305.17247v1",
      "page": 102,
      "image_index": 1,
      "file_size": 568596,
      "format": "jpeg"
    },
    {
      "filename": "2305_17247v1_p104_img1.jpeg",
      "arxiv_id": "2305.17247v1",
      "title": "The Araucaria Project: Improving the cosmic distance scale",
      "authors": [
        "The Araucaria Project",
        ":",
        "G. Pietrzyński"
      ],
      "published": "2023-05-26",
      "arxiv_url": "http://arxiv.org/abs/2305.17247v1",
      "pdf_url": "https://arxiv.org/pdf/2305.17247v1",
      "page": 104,
      "image_index": 1,
      "file_size": 456791,
      "format": "jpeg"
    },
    {
      "filename": "2305_17247v1_p105_img1.jpeg",
      "arxiv_id": "2305.17247v1",
      "title": "The Araucaria Project: Improving the cosmic distance scale",
      "authors": [
        "The Araucaria Project",
        ":",
        "G. Pietrzyński"
      ],
      "published": "2023-05-26",
      "arxiv_url": "http://arxiv.org/abs/2305.17247v1",
      "pdf_url": "https://arxiv.org/pdf/2305.17247v1",
      "page": 105,
      "image_index": 1,
      "file_size": 167137,
      "format": "jpeg"
    },
    {
      "filename": "2305_17247v1_p105_img2.jpeg",
      "arxiv_id": "2305.17247v1",
      "title": "The Araucaria Project: Improving the cosmic distance scale",
      "authors": [
        "The Araucaria Project",
        ":",
        "G. Pietrzyński"
      ],
      "published": "2023-05-26",
      "arxiv_url": "http://arxiv.org/abs/2305.17247v1",
      "pdf_url": "https://arxiv.org/pdf/2305.17247v1",
      "page": 105,
      "image_index": 2,
      "file_size": 182841,
      "format": "jpeg"
    },
    {
      "filename": "2305_17247v1_p105_img3.jpeg",
      "arxiv_id": "2305.17247v1",
      "title": "The Araucaria Project: Improving the cosmic distance scale",
      "authors": [
        "The Araucaria Project",
        ":",
        "G. Pietrzyński"
      ],
      "published": "2023-05-26",
      "arxiv_url": "http://arxiv.org/abs/2305.17247v1",
      "pdf_url": "https://arxiv.org/pdf/2305.17247v1",
      "page": 105,
      "image_index": 3,
      "file_size": 147297,
      "format": "jpeg"
    },
    {
      "filename": "2305_17247v1_p105_img4.jpeg",
      "arxiv_id": "2305.17247v1",
      "title": "The Araucaria Project: Improving the cosmic distance scale",
      "authors": [
        "The Araucaria Project",
        ":",
        "G. Pietrzyński"
      ],
      "published": "2023-05-26",
      "arxiv_url": "http://arxiv.org/abs/2305.17247v1",
      "pdf_url": "https://arxiv.org/pdf/2305.17247v1",
      "page": 105,
      "image_index": 4,
      "file_size": 106206,
      "format": "jpeg"
    },
    {
      "filename": "2305_17247v1_p105_img5.jpeg",
      "arxiv_id": "2305.17247v1",
      "title": "The Araucaria Project: Improving the cosmic distance scale",
      "authors": [
        "The Araucaria Project",
        ":",
        "G. Pietrzyński"
      ],
      "published": "2023-05-26",
      "arxiv_url": "http://arxiv.org/abs/2305.17247v1",
      "pdf_url": "https://arxiv.org/pdf/2305.17247v1",
      "page": 105,
      "image_index": 5,
      "file_size": 97416,
      "format": "jpeg"
    },
    {
      "filename": "2305_17247v1_p105_img6.jpeg",
      "arxiv_id": "2305.17247v1",
      "title": "The Araucaria Project: Improving the cosmic distance scale",
      "authors": [
        "The Araucaria Project",
        ":",
        "G. Pietrzyński"
      ],
      "published": "2023-05-26",
      "arxiv_url": "http://arxiv.org/abs/2305.17247v1",
      "pdf_url": "https://arxiv.org/pdf/2305.17247v1",
      "page": 105,
      "image_index": 6,
      "file_size": 179942,
      "format": "jpeg"
    },
    {
      "filename": "2305_17247v1_p105_img7.jpeg",
      "arxiv_id": "2305.17247v1",
      "title": "The Araucaria Project: Improving the cosmic distance scale",
      "authors": [
        "The Araucaria Project",
        ":",
        "G. Pietrzyński"
      ],
      "published": "2023-05-26",
      "arxiv_url": "http://arxiv.org/abs/2305.17247v1",
      "pdf_url": "https://arxiv.org/pdf/2305.17247v1",
      "page": 105,
      "image_index": 7,
      "file_size": 136527,
      "format": "jpeg"
    },
    {
      "filename": "2305_17247v1_p105_img8.jpeg",
      "arxiv_id": "2305.17247v1",
      "title": "The Araucaria Project: Improving the cosmic distance scale",
      "authors": [
        "The Araucaria Project",
        ":",
        "G. Pietrzyński"
      ],
      "published": "2023-05-26",
      "arxiv_url": "http://arxiv.org/abs/2305.17247v1",
      "pdf_url": "https://arxiv.org/pdf/2305.17247v1",
      "page": 105,
      "image_index": 8,
      "file_size": 108930,
      "format": "jpeg"
    },
    {
      "filename": "2305_17247v1_p105_img9.jpeg",
      "arxiv_id": "2305.17247v1",
      "title": "The Araucaria Project: Improving the cosmic distance scale",
      "authors": [
        "The Araucaria Project",
        ":",
        "G. Pietrzyński"
      ],
      "published": "2023-05-26",
      "arxiv_url": "http://arxiv.org/abs/2305.17247v1",
      "pdf_url": "https://arxiv.org/pdf/2305.17247v1",
      "page": 105,
      "image_index": 9,
      "file_size": 160967,
      "format": "jpeg"
    },
    {
      "filename": "2305_17247v1_p105_img10.jpeg",
      "arxiv_id": "2305.17247v1",
      "title": "The Araucaria Project: Improving the cosmic distance scale",
      "authors": [
        "The Araucaria Project",
        ":",
        "G. Pietrzyński"
      ],
      "published": "2023-05-26",
      "arxiv_url": "http://arxiv.org/abs/2305.17247v1",
      "pdf_url": "https://arxiv.org/pdf/2305.17247v1",
      "page": 105,
      "image_index": 10,
      "file_size": 112605,
      "format": "jpeg"
    },
    {
      "filename": "2305_17247v1_p105_img11.jpeg",
      "arxiv_id": "2305.17247v1",
      "title": "The Araucaria Project: Improving the cosmic distance scale",
      "authors": [
        "The Araucaria Project",
        ":",
        "G. Pietrzyński"
      ],
      "published": "2023-05-26",
      "arxiv_url": "http://arxiv.org/abs/2305.17247v1",
      "pdf_url": "https://arxiv.org/pdf/2305.17247v1",
      "page": 105,
      "image_index": 11,
      "file_size": 155935,
      "format": "jpeg"
    },
    {
      "filename": "2305_17247v1_p106_img1.jpeg",
      "arxiv_id": "2305.17247v1",
      "title": "The Araucaria Project: Improving the cosmic distance scale",
      "authors": [
        "The Araucaria Project",
        ":",
        "G. Pietrzyński"
      ],
      "published": "2023-05-26",
      "arxiv_url": "http://arxiv.org/abs/2305.17247v1",
      "pdf_url": "https://arxiv.org/pdf/2305.17247v1",
      "page": 106,
      "image_index": 1,
      "file_size": 137303,
      "format": "jpeg"
    },
    {
      "filename": "2305_17247v1_p106_img2.jpeg",
      "arxiv_id": "2305.17247v1",
      "title": "The Araucaria Project: Improving the cosmic distance scale",
      "authors": [
        "The Araucaria Project",
        ":",
        "G. Pietrzyński"
      ],
      "published": "2023-05-26",
      "arxiv_url": "http://arxiv.org/abs/2305.17247v1",
      "pdf_url": "https://arxiv.org/pdf/2305.17247v1",
      "page": 106,
      "image_index": 2,
      "file_size": 114401,
      "format": "jpeg"
    },
    {
      "filename": "2305_17247v1_p106_img3.jpeg",
      "arxiv_id": "2305.17247v1",
      "title": "The Araucaria Project: Improving the cosmic distance scale",
      "authors": [
        "The Araucaria Project",
        ":",
        "G. Pietrzyński"
      ],
      "published": "2023-05-26",
      "arxiv_url": "http://arxiv.org/abs/2305.17247v1",
      "pdf_url": "https://arxiv.org/pdf/2305.17247v1",
      "page": 106,
      "image_index": 3,
      "file_size": 129124,
      "format": "jpeg"
    },
    {
      "filename": "2305_17247v1_p106_img4.jpeg",
      "arxiv_id": "2305.17247v1",
      "title": "The Araucaria Project: Improving the cosmic distance scale",
      "authors": [
        "The Araucaria Project",
        ":",
        "G. Pietrzyński"
      ],
      "published": "2023-05-26",
      "arxiv_url": "http://arxiv.org/abs/2305.17247v1",
      "pdf_url": "https://arxiv.org/pdf/2305.17247v1",
      "page": 106,
      "image_index": 4,
      "file_size": 192443,
      "format": "jpeg"
    },
    {
      "filename": "2305_17247v1_p106_img5.jpeg",
      "arxiv_id": "2305.17247v1",
      "title": "The Araucaria Project: Improving the cosmic distance scale",
      "authors": [
        "The Araucaria Project",
        ":",
        "G. Pietrzyński"
      ],
      "published": "2023-05-26",
      "arxiv_url": "http://arxiv.org/abs/2305.17247v1",
      "pdf_url": "https://arxiv.org/pdf/2305.17247v1",
      "page": 106,
      "image_index": 5,
      "file_size": 173716,
      "format": "jpeg"
    },
    {
      "filename": "2305_17247v1_p106_img6.jpeg",
      "arxiv_id": "2305.17247v1",
      "title": "The Araucaria Project: Improving the cosmic distance scale",
      "authors": [
        "The Araucaria Project",
        ":",
        "G. Pietrzyński"
      ],
      "published": "2023-05-26",
      "arxiv_url": "http://arxiv.org/abs/2305.17247v1",
      "pdf_url": "https://arxiv.org/pdf/2305.17247v1",
      "page": 106,
      "image_index": 6,
      "file_size": 133208,
      "format": "jpeg"
    },
    {
      "filename": "2305_17247v1_p106_img7.jpeg",
      "arxiv_id": "2305.17247v1",
      "title": "The Araucaria Project: Improving the cosmic distance scale",
      "authors": [
        "The Araucaria Project",
        ":",
        "G. Pietrzyński"
      ],
      "published": "2023-05-26",
      "arxiv_url": "http://arxiv.org/abs/2305.17247v1",
      "pdf_url": "https://arxiv.org/pdf/2305.17247v1",
      "page": 106,
      "image_index": 7,
      "file_size": 132026,
      "format": "jpeg"
    },
    {
      "filename": "2305_17247v1_p106_img8.jpeg",
      "arxiv_id": "2305.17247v1",
      "title": "The Araucaria Project: Improving the cosmic distance scale",
      "authors": [
        "The Araucaria Project",
        ":",
        "G. Pietrzyński"
      ],
      "published": "2023-05-26",
      "arxiv_url": "http://arxiv.org/abs/2305.17247v1",
      "pdf_url": "https://arxiv.org/pdf/2305.17247v1",
      "page": 106,
      "image_index": 8,
      "file_size": 134298,
      "format": "jpeg"
    },
    {
      "filename": "2305_17247v1_p106_img9.jpeg",
      "arxiv_id": "2305.17247v1",
      "title": "The Araucaria Project: Improving the cosmic distance scale",
      "authors": [
        "The Araucaria Project",
        ":",
        "G. Pietrzyński"
      ],
      "published": "2023-05-26",
      "arxiv_url": "http://arxiv.org/abs/2305.17247v1",
      "pdf_url": "https://arxiv.org/pdf/2305.17247v1",
      "page": 106,
      "image_index": 9,
      "file_size": 141927,
      "format": "jpeg"
    },
    {
      "filename": "2305_17247v1_p106_img10.jpeg",
      "arxiv_id": "2305.17247v1",
      "title": "The Araucaria Project: Improving the cosmic distance scale",
      "authors": [
        "The Araucaria Project",
        ":",
        "G. Pietrzyński"
      ],
      "published": "2023-05-26",
      "arxiv_url": "http://arxiv.org/abs/2305.17247v1",
      "pdf_url": "https://arxiv.org/pdf/2305.17247v1",
      "page": 106,
      "image_index": 10,
      "file_size": 139582,
      "format": "jpeg"
    },
    {
      "filename": "2305_17247v1_p106_img11.jpeg",
      "arxiv_id": "2305.17247v1",
      "title": "The Araucaria Project: Improving the cosmic distance scale",
      "authors": [
        "The Araucaria Project",
        ":",
        "G. Pietrzyński"
      ],
      "published": "2023-05-26",
      "arxiv_url": "http://arxiv.org/abs/2305.17247v1",
      "pdf_url": "https://arxiv.org/pdf/2305.17247v1",
      "page": 106,
      "image_index": 11,
      "file_size": 117544,
      "format": "jpeg"
    },
    {
      "filename": "2305_17247v1_p107_img1.jpeg",
      "arxiv_id": "2305.17247v1",
      "title": "The Araucaria Project: Improving the cosmic distance scale",
      "authors": [
        "The Araucaria Project",
        ":",
        "G. Pietrzyński"
      ],
      "published": "2023-05-26",
      "arxiv_url": "http://arxiv.org/abs/2305.17247v1",
      "pdf_url": "https://arxiv.org/pdf/2305.17247v1",
      "page": 107,
      "image_index": 1,
      "file_size": 809538,
      "format": "jpeg"
    },
    {
      "filename": "2305_17247v1_p107_img2.jpeg",
      "arxiv_id": "2305.17247v1",
      "title": "The Araucaria Project: Improving the cosmic distance scale",
      "authors": [
        "The Araucaria Project",
        ":",
        "G. Pietrzyński"
      ],
      "published": "2023-05-26",
      "arxiv_url": "http://arxiv.org/abs/2305.17247v1",
      "pdf_url": "https://arxiv.org/pdf/2305.17247v1",
      "page": 107,
      "image_index": 2,
      "file_size": 592284,
      "format": "jpeg"
    },
    {
      "filename": "2305_17247v1_p107_img3.jpeg",
      "arxiv_id": "2305.17247v1",
      "title": "The Araucaria Project: Improving the cosmic distance scale",
      "authors": [
        "The Araucaria Project",
        ":",
        "G. Pietrzyński"
      ],
      "published": "2023-05-26",
      "arxiv_url": "http://arxiv.org/abs/2305.17247v1",
      "pdf_url": "https://arxiv.org/pdf/2305.17247v1",
      "page": 107,
      "image_index": 3,
      "file_size": 606139,
      "format": "jpeg"
    },
    {
      "filename": "2305_17247v1_p108_img1.jpeg",
      "arxiv_id": "2305.17247v1",
      "title": "The Araucaria Project: Improving the cosmic distance scale",
      "authors": [
        "The Araucaria Project",
        ":",
        "G. Pietrzyński"
      ],
      "published": "2023-05-26",
      "arxiv_url": "http://arxiv.org/abs/2305.17247v1",
      "pdf_url": "https://arxiv.org/pdf/2305.17247v1",
      "page": 108,
      "image_index": 1,
      "file_size": 1284418,
      "format": "jpeg"
    },
    {
      "filename": "2305_17247v1_p108_img2.jpeg",
      "arxiv_id": "2305.17247v1",
      "title": "The Araucaria Project: Improving the cosmic distance scale",
      "authors": [
        "The Araucaria Project",
        ":",
        "G. Pietrzyński"
      ],
      "published": "2023-05-26",
      "arxiv_url": "http://arxiv.org/abs/2305.17247v1",
      "pdf_url": "https://arxiv.org/pdf/2305.17247v1",
      "page": 108,
      "image_index": 2,
      "file_size": 542298,
      "format": "jpeg"
    },
    {
      "filename": "2305_17247v1_p108_img3.jpeg",
      "arxiv_id": "2305.17247v1",
      "title": "The Araucaria Project: Improving the cosmic distance scale",
      "authors": [
        "The Araucaria Project",
        ":",
        "G. Pietrzyński"
      ],
      "published": "2023-05-26",
      "arxiv_url": "http://arxiv.org/abs/2305.17247v1",
      "pdf_url": "https://arxiv.org/pdf/2305.17247v1",
      "page": 108,
      "image_index": 3,
      "file_size": 422374,
      "format": "jpeg"
    },
    {
      "filename": "2305_17247v1_p109_img1.jpeg",
      "arxiv_id": "2305.17247v1",
      "title": "The Araucaria Project: Improving the cosmic distance scale",
      "authors": [
        "The Araucaria Project",
        ":",
        "G. Pietrzyński"
      ],
      "published": "2023-05-26",
      "arxiv_url": "http://arxiv.org/abs/2305.17247v1",
      "pdf_url": "https://arxiv.org/pdf/2305.17247v1",
      "page": 109,
      "image_index": 1,
      "file_size": 738871,
      "format": "jpeg"
    },
    {
      "filename": "2305_17247v1_p109_img2.jpeg",
      "arxiv_id": "2305.17247v1",
      "title": "The Araucaria Project: Improving the cosmic distance scale",
      "authors": [
        "The Araucaria Project",
        ":",
        "G. Pietrzyński"
      ],
      "published": "2023-05-26",
      "arxiv_url": "http://arxiv.org/abs/2305.17247v1",
      "pdf_url": "https://arxiv.org/pdf/2305.17247v1",
      "page": 109,
      "image_index": 2,
      "file_size": 592618,
      "format": "jpeg"
    },
    {
      "filename": "2305_17247v1_p110_img1.jpeg",
      "arxiv_id": "2305.17247v1",
      "title": "The Araucaria Project: Improving the cosmic distance scale",
      "authors": [
        "The Araucaria Project",
        ":",
        "G. Pietrzyński"
      ],
      "published": "2023-05-26",
      "arxiv_url": "http://arxiv.org/abs/2305.17247v1",
      "pdf_url": "https://arxiv.org/pdf/2305.17247v1",
      "page": 110,
      "image_index": 1,
      "file_size": 749686,
      "format": "jpeg"
    },
    {
      "filename": "2305_17247v1_p110_img2.jpeg",
      "arxiv_id": "2305.17247v1",
      "title": "The Araucaria Project: Improving the cosmic distance scale",
      "authors": [
        "The Araucaria Project",
        ":",
        "G. Pietrzyński"
      ],
      "published": "2023-05-26",
      "arxiv_url": "http://arxiv.org/abs/2305.17247v1",
      "pdf_url": "https://arxiv.org/pdf/2305.17247v1",
      "page": 110,
      "image_index": 2,
      "file_size": 647330,
      "format": "jpeg"
    },
    {
      "filename": "2305_17247v1_p110_img3.jpeg",
      "arxiv_id": "2305.17247v1",
      "title": "The Araucaria Project: Improving the cosmic distance scale",
      "authors": [
        "The Araucaria Project",
        ":",
        "G. Pietrzyński"
      ],
      "published": "2023-05-26",
      "arxiv_url": "http://arxiv.org/abs/2305.17247v1",
      "pdf_url": "https://arxiv.org/pdf/2305.17247v1",
      "page": 110,
      "image_index": 3,
      "file_size": 335015,
      "format": "jpeg"
    },
    {
      "filename": "2305_17247v1_p111_img1.jpeg",
      "arxiv_id": "2305.17247v1",
      "title": "The Araucaria Project: Improving the cosmic distance scale",
      "authors": [
        "The Araucaria Project",
        ":",
        "G. Pietrzyński"
      ],
      "published": "2023-05-26",
      "arxiv_url": "http://arxiv.org/abs/2305.17247v1",
      "pdf_url": "https://arxiv.org/pdf/2305.17247v1",
      "page": 111,
      "image_index": 1,
      "file_size": 335452,
      "format": "jpeg"
    },
    {
      "filename": "2305_17247v1_p111_img2.jpeg",
      "arxiv_id": "2305.17247v1",
      "title": "The Araucaria Project: Improving the cosmic distance scale",
      "authors": [
        "The Araucaria Project",
        ":",
        "G. Pietrzyński"
      ],
      "published": "2023-05-26",
      "arxiv_url": "http://arxiv.org/abs/2305.17247v1",
      "pdf_url": "https://arxiv.org/pdf/2305.17247v1",
      "page": 111,
      "image_index": 2,
      "file_size": 309121,
      "format": "jpeg"
    },
    {
      "filename": "2305_17247v1_p111_img3.jpeg",
      "arxiv_id": "2305.17247v1",
      "title": "The Araucaria Project: Improving the cosmic distance scale",
      "authors": [
        "The Araucaria Project",
        ":",
        "G. Pietrzyński"
      ],
      "published": "2023-05-26",
      "arxiv_url": "http://arxiv.org/abs/2305.17247v1",
      "pdf_url": "https://arxiv.org/pdf/2305.17247v1",
      "page": 111,
      "image_index": 3,
      "file_size": 326281,
      "format": "jpeg"
    },
    {
      "filename": "2305_17247v1_p111_img4.jpeg",
      "arxiv_id": "2305.17247v1",
      "title": "The Araucaria Project: Improving the cosmic distance scale",
      "authors": [
        "The Araucaria Project",
        ":",
        "G. Pietrzyński"
      ],
      "published": "2023-05-26",
      "arxiv_url": "http://arxiv.org/abs/2305.17247v1",
      "pdf_url": "https://arxiv.org/pdf/2305.17247v1",
      "page": 111,
      "image_index": 4,
      "file_size": 612034,
      "format": "jpeg"
    },
    {
      "filename": "2305_17247v1_p111_img5.jpeg",
      "arxiv_id": "2305.17247v1",
      "title": "The Araucaria Project: Improving the cosmic distance scale",
      "authors": [
        "The Araucaria Project",
        ":",
        "G. Pietrzyński"
      ],
      "published": "2023-05-26",
      "arxiv_url": "http://arxiv.org/abs/2305.17247v1",
      "pdf_url": "https://arxiv.org/pdf/2305.17247v1",
      "page": 111,
      "image_index": 5,
      "file_size": 322560,
      "format": "jpeg"
    },
    {
      "filename": "2305_17247v1_p111_img6.jpeg",
      "arxiv_id": "2305.17247v1",
      "title": "The Araucaria Project: Improving the cosmic distance scale",
      "authors": [
        "The Araucaria Project",
        ":",
        "G. Pietrzyński"
      ],
      "published": "2023-05-26",
      "arxiv_url": "http://arxiv.org/abs/2305.17247v1",
      "pdf_url": "https://arxiv.org/pdf/2305.17247v1",
      "page": 111,
      "image_index": 6,
      "file_size": 436531,
      "format": "jpeg"
    },
    {
      "filename": "2305_17247v1_p112_img1.png",
      "arxiv_id": "2305.17247v1",
      "title": "The Araucaria Project: Improving the cosmic distance scale",
      "authors": [
        "The Araucaria Project",
        ":",
        "G. Pietrzyński"
      ],
      "published": "2023-05-26",
      "arxiv_url": "http://arxiv.org/abs/2305.17247v1",
      "pdf_url": "https://arxiv.org/pdf/2305.17247v1",
      "page": 112,
      "image_index": 1,
      "file_size": 5106,
      "format": "png"
    },
    {
      "filename": "2305_17247v1_p112_img2.jpeg",
      "arxiv_id": "2305.17247v1",
      "title": "The Araucaria Project: Improving the cosmic distance scale",
      "authors": [
        "The Araucaria Project",
        ":",
        "G. Pietrzyński"
      ],
      "published": "2023-05-26",
      "arxiv_url": "http://arxiv.org/abs/2305.17247v1",
      "pdf_url": "https://arxiv.org/pdf/2305.17247v1",
      "page": 112,
      "image_index": 2,
      "file_size": 1465550,
      "format": "jpeg"
    },
    {
      "filename": "2305_17247v1_p112_img3.png",
      "arxiv_id": "2305.17247v1",
      "title": "The Araucaria Project: Improving the cosmic distance scale",
      "authors": [
        "The Araucaria Project",
        ":",
        "G. Pietrzyński"
      ],
      "published": "2023-05-26",
      "arxiv_url": "http://arxiv.org/abs/2305.17247v1",
      "pdf_url": "https://arxiv.org/pdf/2305.17247v1",
      "page": 112,
      "image_index": 3,
      "file_size": 29259,
      "format": "png"
    },
    {
      "filename": "2305_17247v1_p112_img4.jpeg",
      "arxiv_id": "2305.17247v1",
      "title": "The Araucaria Project: Improving the cosmic distance scale",
      "authors": [
        "The Araucaria Project",
        ":",
        "G. Pietrzyński"
      ],
      "published": "2023-05-26",
      "arxiv_url": "http://arxiv.org/abs/2305.17247v1",
      "pdf_url": "https://arxiv.org/pdf/2305.17247v1",
      "page": 112,
      "image_index": 4,
      "file_size": 24811,
      "format": "jpeg"
    },
    {
      "filename": "2305_17247v1_p112_img5.jpeg",
      "arxiv_id": "2305.17247v1",
      "title": "The Araucaria Project: Improving the cosmic distance scale",
      "authors": [
        "The Araucaria Project",
        ":",
        "G. Pietrzyński"
      ],
      "published": "2023-05-26",
      "arxiv_url": "http://arxiv.org/abs/2305.17247v1",
      "pdf_url": "https://arxiv.org/pdf/2305.17247v1",
      "page": 112,
      "image_index": 5,
      "file_size": 15771,
      "format": "jpeg"
    },
    {
      "filename": "2507_05322v1_p7_img1.png",
      "arxiv_id": "2507.05322v1",
      "title": "Dataless Neural Networks for Resource-Constrained Project Scheduling",
      "authors": [
        "Marc Bara"
      ],
      "published": "2025-07-07",
      "arxiv_url": "http://arxiv.org/abs/2507.05322v1",
      "pdf_url": "https://arxiv.org/pdf/2507.05322v1",
      "page": 7,
      "image_index": 1,
      "file_size": 310055,
      "format": "png"
    },
    {
      "filename": "2505_20861v1_p1_img2.jpeg",
      "arxiv_id": "2505.20861v1",
      "title": "Exploring Timeline Control for Facial Motion Generation",
      "authors": [
        "Yifeng Ma",
        "Jinwei Qi",
        "Chaonan Ji"
      ],
      "published": "2025-05-27",
      "arxiv_url": "http://arxiv.org/abs/2505.20861v1",
      "pdf_url": "https://arxiv.org/pdf/2505.20861v1",
      "page": 1,
      "image_index": 2,
      "file_size": 13327,
      "format": "jpeg"
    },
    {
      "filename": "2505_20861v1_p1_img3.jpeg",
      "arxiv_id": "2505.20861v1",
      "title": "Exploring Timeline Control for Facial Motion Generation",
      "authors": [
        "Yifeng Ma",
        "Jinwei Qi",
        "Chaonan Ji"
      ],
      "published": "2025-05-27",
      "arxiv_url": "http://arxiv.org/abs/2505.20861v1",
      "pdf_url": "https://arxiv.org/pdf/2505.20861v1",
      "page": 1,
      "image_index": 3,
      "file_size": 13163,
      "format": "jpeg"
    },
    {
      "filename": "2505_20861v1_p1_img4.jpeg",
      "arxiv_id": "2505.20861v1",
      "title": "Exploring Timeline Control for Facial Motion Generation",
      "authors": [
        "Yifeng Ma",
        "Jinwei Qi",
        "Chaonan Ji"
      ],
      "published": "2025-05-27",
      "arxiv_url": "http://arxiv.org/abs/2505.20861v1",
      "pdf_url": "https://arxiv.org/pdf/2505.20861v1",
      "page": 1,
      "image_index": 4,
      "file_size": 47833,
      "format": "jpeg"
    },
    {
      "filename": "2505_20861v1_p1_img5.jpeg",
      "arxiv_id": "2505.20861v1",
      "title": "Exploring Timeline Control for Facial Motion Generation",
      "authors": [
        "Yifeng Ma",
        "Jinwei Qi",
        "Chaonan Ji"
      ],
      "published": "2025-05-27",
      "arxiv_url": "http://arxiv.org/abs/2505.20861v1",
      "pdf_url": "https://arxiv.org/pdf/2505.20861v1",
      "page": 1,
      "image_index": 5,
      "file_size": 44582,
      "format": "jpeg"
    },
    {
      "filename": "2505_20861v1_p1_img6.jpeg",
      "arxiv_id": "2505.20861v1",
      "title": "Exploring Timeline Control for Facial Motion Generation",
      "authors": [
        "Yifeng Ma",
        "Jinwei Qi",
        "Chaonan Ji"
      ],
      "published": "2025-05-27",
      "arxiv_url": "http://arxiv.org/abs/2505.20861v1",
      "pdf_url": "https://arxiv.org/pdf/2505.20861v1",
      "page": 1,
      "image_index": 6,
      "file_size": 46720,
      "format": "jpeg"
    },
    {
      "filename": "2505_20861v1_p1_img7.jpeg",
      "arxiv_id": "2505.20861v1",
      "title": "Exploring Timeline Control for Facial Motion Generation",
      "authors": [
        "Yifeng Ma",
        "Jinwei Qi",
        "Chaonan Ji"
      ],
      "published": "2025-05-27",
      "arxiv_url": "http://arxiv.org/abs/2505.20861v1",
      "pdf_url": "https://arxiv.org/pdf/2505.20861v1",
      "page": 1,
      "image_index": 7,
      "file_size": 45954,
      "format": "jpeg"
    },
    {
      "filename": "2505_20861v1_p1_img8.jpeg",
      "arxiv_id": "2505.20861v1",
      "title": "Exploring Timeline Control for Facial Motion Generation",
      "authors": [
        "Yifeng Ma",
        "Jinwei Qi",
        "Chaonan Ji"
      ],
      "published": "2025-05-27",
      "arxiv_url": "http://arxiv.org/abs/2505.20861v1",
      "pdf_url": "https://arxiv.org/pdf/2505.20861v1",
      "page": 1,
      "image_index": 8,
      "file_size": 45083,
      "format": "jpeg"
    },
    {
      "filename": "2505_20861v1_p1_img9.jpeg",
      "arxiv_id": "2505.20861v1",
      "title": "Exploring Timeline Control for Facial Motion Generation",
      "authors": [
        "Yifeng Ma",
        "Jinwei Qi",
        "Chaonan Ji"
      ],
      "published": "2025-05-27",
      "arxiv_url": "http://arxiv.org/abs/2505.20861v1",
      "pdf_url": "https://arxiv.org/pdf/2505.20861v1",
      "page": 1,
      "image_index": 9,
      "file_size": 40150,
      "format": "jpeg"
    },
    {
      "filename": "2505_20861v1_p1_img10.jpeg",
      "arxiv_id": "2505.20861v1",
      "title": "Exploring Timeline Control for Facial Motion Generation",
      "authors": [
        "Yifeng Ma",
        "Jinwei Qi",
        "Chaonan Ji"
      ],
      "published": "2025-05-27",
      "arxiv_url": "http://arxiv.org/abs/2505.20861v1",
      "pdf_url": "https://arxiv.org/pdf/2505.20861v1",
      "page": 1,
      "image_index": 10,
      "file_size": 13010,
      "format": "jpeg"
    },
    {
      "filename": "2505_20861v1_p1_img11.jpeg",
      "arxiv_id": "2505.20861v1",
      "title": "Exploring Timeline Control for Facial Motion Generation",
      "authors": [
        "Yifeng Ma",
        "Jinwei Qi",
        "Chaonan Ji"
      ],
      "published": "2025-05-27",
      "arxiv_url": "http://arxiv.org/abs/2505.20861v1",
      "pdf_url": "https://arxiv.org/pdf/2505.20861v1",
      "page": 1,
      "image_index": 11,
      "file_size": 13174,
      "format": "jpeg"
    },
    {
      "filename": "2505_20861v1_p3_img1.jpeg",
      "arxiv_id": "2505.20861v1",
      "title": "Exploring Timeline Control for Facial Motion Generation",
      "authors": [
        "Yifeng Ma",
        "Jinwei Qi",
        "Chaonan Ji"
      ],
      "published": "2025-05-27",
      "arxiv_url": "http://arxiv.org/abs/2505.20861v1",
      "pdf_url": "https://arxiv.org/pdf/2505.20861v1",
      "page": 3,
      "image_index": 1,
      "file_size": 42539,
      "format": "jpeg"
    },
    {
      "filename": "2505_20861v1_p3_img2.jpeg",
      "arxiv_id": "2505.20861v1",
      "title": "Exploring Timeline Control for Facial Motion Generation",
      "authors": [
        "Yifeng Ma",
        "Jinwei Qi",
        "Chaonan Ji"
      ],
      "published": "2025-05-27",
      "arxiv_url": "http://arxiv.org/abs/2505.20861v1",
      "pdf_url": "https://arxiv.org/pdf/2505.20861v1",
      "page": 3,
      "image_index": 2,
      "file_size": 18098,
      "format": "jpeg"
    },
    {
      "filename": "2505_20861v1_p3_img3.jpeg",
      "arxiv_id": "2505.20861v1",
      "title": "Exploring Timeline Control for Facial Motion Generation",
      "authors": [
        "Yifeng Ma",
        "Jinwei Qi",
        "Chaonan Ji"
      ],
      "published": "2025-05-27",
      "arxiv_url": "http://arxiv.org/abs/2505.20861v1",
      "pdf_url": "https://arxiv.org/pdf/2505.20861v1",
      "page": 3,
      "image_index": 3,
      "file_size": 16700,
      "format": "jpeg"
    },
    {
      "filename": "2505_20861v1_p3_img4.png",
      "arxiv_id": "2505.20861v1",
      "title": "Exploring Timeline Control for Facial Motion Generation",
      "authors": [
        "Yifeng Ma",
        "Jinwei Qi",
        "Chaonan Ji"
      ],
      "published": "2025-05-27",
      "arxiv_url": "http://arxiv.org/abs/2505.20861v1",
      "pdf_url": "https://arxiv.org/pdf/2505.20861v1",
      "page": 3,
      "image_index": 4,
      "file_size": 10031,
      "format": "png"
    },
    {
      "filename": "2505_20861v1_p3_img5.jpeg",
      "arxiv_id": "2505.20861v1",
      "title": "Exploring Timeline Control for Facial Motion Generation",
      "authors": [
        "Yifeng Ma",
        "Jinwei Qi",
        "Chaonan Ji"
      ],
      "published": "2025-05-27",
      "arxiv_url": "http://arxiv.org/abs/2505.20861v1",
      "pdf_url": "https://arxiv.org/pdf/2505.20861v1",
      "page": 3,
      "image_index": 5,
      "file_size": 40983,
      "format": "jpeg"
    },
    {
      "filename": "2505_20861v1_p3_img6.jpeg",
      "arxiv_id": "2505.20861v1",
      "title": "Exploring Timeline Control for Facial Motion Generation",
      "authors": [
        "Yifeng Ma",
        "Jinwei Qi",
        "Chaonan Ji"
      ],
      "published": "2025-05-27",
      "arxiv_url": "http://arxiv.org/abs/2505.20861v1",
      "pdf_url": "https://arxiv.org/pdf/2505.20861v1",
      "page": 3,
      "image_index": 6,
      "file_size": 40719,
      "format": "jpeg"
    },
    {
      "filename": "2505_20861v1_p3_img7.png",
      "arxiv_id": "2505.20861v1",
      "title": "Exploring Timeline Control for Facial Motion Generation",
      "authors": [
        "Yifeng Ma",
        "Jinwei Qi",
        "Chaonan Ji"
      ],
      "published": "2025-05-27",
      "arxiv_url": "http://arxiv.org/abs/2505.20861v1",
      "pdf_url": "https://arxiv.org/pdf/2505.20861v1",
      "page": 3,
      "image_index": 7,
      "file_size": 10720,
      "format": "png"
    },
    {
      "filename": "2505_20861v1_p3_img8.jpeg",
      "arxiv_id": "2505.20861v1",
      "title": "Exploring Timeline Control for Facial Motion Generation",
      "authors": [
        "Yifeng Ma",
        "Jinwei Qi",
        "Chaonan Ji"
      ],
      "published": "2025-05-27",
      "arxiv_url": "http://arxiv.org/abs/2505.20861v1",
      "pdf_url": "https://arxiv.org/pdf/2505.20861v1",
      "page": 3,
      "image_index": 8,
      "file_size": 41659,
      "format": "jpeg"
    },
    {
      "filename": "2505_20861v1_p3_img9.png",
      "arxiv_id": "2505.20861v1",
      "title": "Exploring Timeline Control for Facial Motion Generation",
      "authors": [
        "Yifeng Ma",
        "Jinwei Qi",
        "Chaonan Ji"
      ],
      "published": "2025-05-27",
      "arxiv_url": "http://arxiv.org/abs/2505.20861v1",
      "pdf_url": "https://arxiv.org/pdf/2505.20861v1",
      "page": 3,
      "image_index": 9,
      "file_size": 6694,
      "format": "png"
    },
    {
      "filename": "2505_20861v1_p3_img10.png",
      "arxiv_id": "2505.20861v1",
      "title": "Exploring Timeline Control for Facial Motion Generation",
      "authors": [
        "Yifeng Ma",
        "Jinwei Qi",
        "Chaonan Ji"
      ],
      "published": "2025-05-27",
      "arxiv_url": "http://arxiv.org/abs/2505.20861v1",
      "pdf_url": "https://arxiv.org/pdf/2505.20861v1",
      "page": 3,
      "image_index": 10,
      "file_size": 12734,
      "format": "png"
    },
    {
      "filename": "2505_20861v1_p3_img11.png",
      "arxiv_id": "2505.20861v1",
      "title": "Exploring Timeline Control for Facial Motion Generation",
      "authors": [
        "Yifeng Ma",
        "Jinwei Qi",
        "Chaonan Ji"
      ],
      "published": "2025-05-27",
      "arxiv_url": "http://arxiv.org/abs/2505.20861v1",
      "pdf_url": "https://arxiv.org/pdf/2505.20861v1",
      "page": 3,
      "image_index": 11,
      "file_size": 6079,
      "format": "png"
    },
    {
      "filename": "2505_20861v1_p3_img12.jpeg",
      "arxiv_id": "2505.20861v1",
      "title": "Exploring Timeline Control for Facial Motion Generation",
      "authors": [
        "Yifeng Ma",
        "Jinwei Qi",
        "Chaonan Ji"
      ],
      "published": "2025-05-27",
      "arxiv_url": "http://arxiv.org/abs/2505.20861v1",
      "pdf_url": "https://arxiv.org/pdf/2505.20861v1",
      "page": 3,
      "image_index": 12,
      "file_size": 10559,
      "format": "jpeg"
    },
    {
      "filename": "2505_20861v1_p4_img1.jpeg",
      "arxiv_id": "2505.20861v1",
      "title": "Exploring Timeline Control for Facial Motion Generation",
      "authors": [
        "Yifeng Ma",
        "Jinwei Qi",
        "Chaonan Ji"
      ],
      "published": "2025-05-27",
      "arxiv_url": "http://arxiv.org/abs/2505.20861v1",
      "pdf_url": "https://arxiv.org/pdf/2505.20861v1",
      "page": 4,
      "image_index": 1,
      "file_size": 39647,
      "format": "jpeg"
    },
    {
      "filename": "2505_20861v1_p4_img2.png",
      "arxiv_id": "2505.20861v1",
      "title": "Exploring Timeline Control for Facial Motion Generation",
      "authors": [
        "Yifeng Ma",
        "Jinwei Qi",
        "Chaonan Ji"
      ],
      "published": "2025-05-27",
      "arxiv_url": "http://arxiv.org/abs/2505.20861v1",
      "pdf_url": "https://arxiv.org/pdf/2505.20861v1",
      "page": 4,
      "image_index": 2,
      "file_size": 74164,
      "format": "png"
    },
    {
      "filename": "2505_20861v1_p4_img3.jpeg",
      "arxiv_id": "2505.20861v1",
      "title": "Exploring Timeline Control for Facial Motion Generation",
      "authors": [
        "Yifeng Ma",
        "Jinwei Qi",
        "Chaonan Ji"
      ],
      "published": "2025-05-27",
      "arxiv_url": "http://arxiv.org/abs/2505.20861v1",
      "pdf_url": "https://arxiv.org/pdf/2505.20861v1",
      "page": 4,
      "image_index": 3,
      "file_size": 148029,
      "format": "jpeg"
    },
    {
      "filename": "2505_20861v1_p4_img5.png",
      "arxiv_id": "2505.20861v1",
      "title": "Exploring Timeline Control for Facial Motion Generation",
      "authors": [
        "Yifeng Ma",
        "Jinwei Qi",
        "Chaonan Ji"
      ],
      "published": "2025-05-27",
      "arxiv_url": "http://arxiv.org/abs/2505.20861v1",
      "pdf_url": "https://arxiv.org/pdf/2505.20861v1",
      "page": 4,
      "image_index": 5,
      "file_size": 29237,
      "format": "png"
    },
    {
      "filename": "2505_20861v1_p4_img6.png",
      "arxiv_id": "2505.20861v1",
      "title": "Exploring Timeline Control for Facial Motion Generation",
      "authors": [
        "Yifeng Ma",
        "Jinwei Qi",
        "Chaonan Ji"
      ],
      "published": "2025-05-27",
      "arxiv_url": "http://arxiv.org/abs/2505.20861v1",
      "pdf_url": "https://arxiv.org/pdf/2505.20861v1",
      "page": 4,
      "image_index": 6,
      "file_size": 32564,
      "format": "png"
    },
    {
      "filename": "2505_20861v1_p4_img7.png",
      "arxiv_id": "2505.20861v1",
      "title": "Exploring Timeline Control for Facial Motion Generation",
      "authors": [
        "Yifeng Ma",
        "Jinwei Qi",
        "Chaonan Ji"
      ],
      "published": "2025-05-27",
      "arxiv_url": "http://arxiv.org/abs/2505.20861v1",
      "pdf_url": "https://arxiv.org/pdf/2505.20861v1",
      "page": 4,
      "image_index": 7,
      "file_size": 34511,
      "format": "png"
    },
    {
      "filename": "2505_20861v1_p4_img8.png",
      "arxiv_id": "2505.20861v1",
      "title": "Exploring Timeline Control for Facial Motion Generation",
      "authors": [
        "Yifeng Ma",
        "Jinwei Qi",
        "Chaonan Ji"
      ],
      "published": "2025-05-27",
      "arxiv_url": "http://arxiv.org/abs/2505.20861v1",
      "pdf_url": "https://arxiv.org/pdf/2505.20861v1",
      "page": 4,
      "image_index": 8,
      "file_size": 16325,
      "format": "png"
    },
    {
      "filename": "2505_20861v1_p4_img9.png",
      "arxiv_id": "2505.20861v1",
      "title": "Exploring Timeline Control for Facial Motion Generation",
      "authors": [
        "Yifeng Ma",
        "Jinwei Qi",
        "Chaonan Ji"
      ],
      "published": "2025-05-27",
      "arxiv_url": "http://arxiv.org/abs/2505.20861v1",
      "pdf_url": "https://arxiv.org/pdf/2505.20861v1",
      "page": 4,
      "image_index": 9,
      "file_size": 20964,
      "format": "png"
    },
    {
      "filename": "2505_20861v1_p4_img10.png",
      "arxiv_id": "2505.20861v1",
      "title": "Exploring Timeline Control for Facial Motion Generation",
      "authors": [
        "Yifeng Ma",
        "Jinwei Qi",
        "Chaonan Ji"
      ],
      "published": "2025-05-27",
      "arxiv_url": "http://arxiv.org/abs/2505.20861v1",
      "pdf_url": "https://arxiv.org/pdf/2505.20861v1",
      "page": 4,
      "image_index": 10,
      "file_size": 286995,
      "format": "png"
    },
    {
      "filename": "2505_20861v1_p4_img11.png",
      "arxiv_id": "2505.20861v1",
      "title": "Exploring Timeline Control for Facial Motion Generation",
      "authors": [
        "Yifeng Ma",
        "Jinwei Qi",
        "Chaonan Ji"
      ],
      "published": "2025-05-27",
      "arxiv_url": "http://arxiv.org/abs/2505.20861v1",
      "pdf_url": "https://arxiv.org/pdf/2505.20861v1",
      "page": 4,
      "image_index": 11,
      "file_size": 61617,
      "format": "png"
    },
    {
      "filename": "2505_20861v1_p6_img1.jpeg",
      "arxiv_id": "2505.20861v1",
      "title": "Exploring Timeline Control for Facial Motion Generation",
      "authors": [
        "Yifeng Ma",
        "Jinwei Qi",
        "Chaonan Ji"
      ],
      "published": "2025-05-27",
      "arxiv_url": "http://arxiv.org/abs/2505.20861v1",
      "pdf_url": "https://arxiv.org/pdf/2505.20861v1",
      "page": 6,
      "image_index": 1,
      "file_size": 15050,
      "format": "jpeg"
    },
    {
      "filename": "2505_20861v1_p6_img2.jpeg",
      "arxiv_id": "2505.20861v1",
      "title": "Exploring Timeline Control for Facial Motion Generation",
      "authors": [
        "Yifeng Ma",
        "Jinwei Qi",
        "Chaonan Ji"
      ],
      "published": "2025-05-27",
      "arxiv_url": "http://arxiv.org/abs/2505.20861v1",
      "pdf_url": "https://arxiv.org/pdf/2505.20861v1",
      "page": 6,
      "image_index": 2,
      "file_size": 15289,
      "format": "jpeg"
    },
    {
      "filename": "2505_20861v1_p6_img3.jpeg",
      "arxiv_id": "2505.20861v1",
      "title": "Exploring Timeline Control for Facial Motion Generation",
      "authors": [
        "Yifeng Ma",
        "Jinwei Qi",
        "Chaonan Ji"
      ],
      "published": "2025-05-27",
      "arxiv_url": "http://arxiv.org/abs/2505.20861v1",
      "pdf_url": "https://arxiv.org/pdf/2505.20861v1",
      "page": 6,
      "image_index": 3,
      "file_size": 14763,
      "format": "jpeg"
    },
    {
      "filename": "2505_20861v1_p6_img4.jpeg",
      "arxiv_id": "2505.20861v1",
      "title": "Exploring Timeline Control for Facial Motion Generation",
      "authors": [
        "Yifeng Ma",
        "Jinwei Qi",
        "Chaonan Ji"
      ],
      "published": "2025-05-27",
      "arxiv_url": "http://arxiv.org/abs/2505.20861v1",
      "pdf_url": "https://arxiv.org/pdf/2505.20861v1",
      "page": 6,
      "image_index": 4,
      "file_size": 14947,
      "format": "jpeg"
    },
    {
      "filename": "2505_20861v1_p6_img5.jpeg",
      "arxiv_id": "2505.20861v1",
      "title": "Exploring Timeline Control for Facial Motion Generation",
      "authors": [
        "Yifeng Ma",
        "Jinwei Qi",
        "Chaonan Ji"
      ],
      "published": "2025-05-27",
      "arxiv_url": "http://arxiv.org/abs/2505.20861v1",
      "pdf_url": "https://arxiv.org/pdf/2505.20861v1",
      "page": 6,
      "image_index": 5,
      "file_size": 18725,
      "format": "jpeg"
    },
    {
      "filename": "2505_20861v1_p6_img6.jpeg",
      "arxiv_id": "2505.20861v1",
      "title": "Exploring Timeline Control for Facial Motion Generation",
      "authors": [
        "Yifeng Ma",
        "Jinwei Qi",
        "Chaonan Ji"
      ],
      "published": "2025-05-27",
      "arxiv_url": "http://arxiv.org/abs/2505.20861v1",
      "pdf_url": "https://arxiv.org/pdf/2505.20861v1",
      "page": 6,
      "image_index": 6,
      "file_size": 18258,
      "format": "jpeg"
    },
    {
      "filename": "2505_20861v1_p6_img7.jpeg",
      "arxiv_id": "2505.20861v1",
      "title": "Exploring Timeline Control for Facial Motion Generation",
      "authors": [
        "Yifeng Ma",
        "Jinwei Qi",
        "Chaonan Ji"
      ],
      "published": "2025-05-27",
      "arxiv_url": "http://arxiv.org/abs/2505.20861v1",
      "pdf_url": "https://arxiv.org/pdf/2505.20861v1",
      "page": 6,
      "image_index": 7,
      "file_size": 18901,
      "format": "jpeg"
    },
    {
      "filename": "2505_20861v1_p6_img8.jpeg",
      "arxiv_id": "2505.20861v1",
      "title": "Exploring Timeline Control for Facial Motion Generation",
      "authors": [
        "Yifeng Ma",
        "Jinwei Qi",
        "Chaonan Ji"
      ],
      "published": "2025-05-27",
      "arxiv_url": "http://arxiv.org/abs/2505.20861v1",
      "pdf_url": "https://arxiv.org/pdf/2505.20861v1",
      "page": 6,
      "image_index": 8,
      "file_size": 18313,
      "format": "jpeg"
    },
    {
      "filename": "2505_20861v1_p7_img1.png",
      "arxiv_id": "2505.20861v1",
      "title": "Exploring Timeline Control for Facial Motion Generation",
      "authors": [
        "Yifeng Ma",
        "Jinwei Qi",
        "Chaonan Ji"
      ],
      "published": "2025-05-27",
      "arxiv_url": "http://arxiv.org/abs/2505.20861v1",
      "pdf_url": "https://arxiv.org/pdf/2505.20861v1",
      "page": 7,
      "image_index": 1,
      "file_size": 55590,
      "format": "png"
    },
    {
      "filename": "2505_20861v1_p7_img2.jpeg",
      "arxiv_id": "2505.20861v1",
      "title": "Exploring Timeline Control for Facial Motion Generation",
      "authors": [
        "Yifeng Ma",
        "Jinwei Qi",
        "Chaonan Ji"
      ],
      "published": "2025-05-27",
      "arxiv_url": "http://arxiv.org/abs/2505.20861v1",
      "pdf_url": "https://arxiv.org/pdf/2505.20861v1",
      "page": 7,
      "image_index": 2,
      "file_size": 37225,
      "format": "jpeg"
    },
    {
      "filename": "2505_20861v1_p7_img3.jpeg",
      "arxiv_id": "2505.20861v1",
      "title": "Exploring Timeline Control for Facial Motion Generation",
      "authors": [
        "Yifeng Ma",
        "Jinwei Qi",
        "Chaonan Ji"
      ],
      "published": "2025-05-27",
      "arxiv_url": "http://arxiv.org/abs/2505.20861v1",
      "pdf_url": "https://arxiv.org/pdf/2505.20861v1",
      "page": 7,
      "image_index": 3,
      "file_size": 37972,
      "format": "jpeg"
    },
    {
      "filename": "2505_20861v1_p7_img4.jpeg",
      "arxiv_id": "2505.20861v1",
      "title": "Exploring Timeline Control for Facial Motion Generation",
      "authors": [
        "Yifeng Ma",
        "Jinwei Qi",
        "Chaonan Ji"
      ],
      "published": "2025-05-27",
      "arxiv_url": "http://arxiv.org/abs/2505.20861v1",
      "pdf_url": "https://arxiv.org/pdf/2505.20861v1",
      "page": 7,
      "image_index": 4,
      "file_size": 37918,
      "format": "jpeg"
    },
    {
      "filename": "2505_20861v1_p7_img5.jpeg",
      "arxiv_id": "2505.20861v1",
      "title": "Exploring Timeline Control for Facial Motion Generation",
      "authors": [
        "Yifeng Ma",
        "Jinwei Qi",
        "Chaonan Ji"
      ],
      "published": "2025-05-27",
      "arxiv_url": "http://arxiv.org/abs/2505.20861v1",
      "pdf_url": "https://arxiv.org/pdf/2505.20861v1",
      "page": 7,
      "image_index": 5,
      "file_size": 35429,
      "format": "jpeg"
    },
    {
      "filename": "2505_20861v1_p7_img6.jpeg",
      "arxiv_id": "2505.20861v1",
      "title": "Exploring Timeline Control for Facial Motion Generation",
      "authors": [
        "Yifeng Ma",
        "Jinwei Qi",
        "Chaonan Ji"
      ],
      "published": "2025-05-27",
      "arxiv_url": "http://arxiv.org/abs/2505.20861v1",
      "pdf_url": "https://arxiv.org/pdf/2505.20861v1",
      "page": 7,
      "image_index": 6,
      "file_size": 38023,
      "format": "jpeg"
    },
    {
      "filename": "2505_20861v1_p7_img7.jpeg",
      "arxiv_id": "2505.20861v1",
      "title": "Exploring Timeline Control for Facial Motion Generation",
      "authors": [
        "Yifeng Ma",
        "Jinwei Qi",
        "Chaonan Ji"
      ],
      "published": "2025-05-27",
      "arxiv_url": "http://arxiv.org/abs/2505.20861v1",
      "pdf_url": "https://arxiv.org/pdf/2505.20861v1",
      "page": 7,
      "image_index": 7,
      "file_size": 34995,
      "format": "jpeg"
    },
    {
      "filename": "2505_20861v1_p7_img8.jpeg",
      "arxiv_id": "2505.20861v1",
      "title": "Exploring Timeline Control for Facial Motion Generation",
      "authors": [
        "Yifeng Ma",
        "Jinwei Qi",
        "Chaonan Ji"
      ],
      "published": "2025-05-27",
      "arxiv_url": "http://arxiv.org/abs/2505.20861v1",
      "pdf_url": "https://arxiv.org/pdf/2505.20861v1",
      "page": 7,
      "image_index": 8,
      "file_size": 40445,
      "format": "jpeg"
    },
    {
      "filename": "2505_20861v1_p7_img9.jpeg",
      "arxiv_id": "2505.20861v1",
      "title": "Exploring Timeline Control for Facial Motion Generation",
      "authors": [
        "Yifeng Ma",
        "Jinwei Qi",
        "Chaonan Ji"
      ],
      "published": "2025-05-27",
      "arxiv_url": "http://arxiv.org/abs/2505.20861v1",
      "pdf_url": "https://arxiv.org/pdf/2505.20861v1",
      "page": 7,
      "image_index": 9,
      "file_size": 32218,
      "format": "jpeg"
    },
    {
      "filename": "2505_20861v1_p7_img10.jpeg",
      "arxiv_id": "2505.20861v1",
      "title": "Exploring Timeline Control for Facial Motion Generation",
      "authors": [
        "Yifeng Ma",
        "Jinwei Qi",
        "Chaonan Ji"
      ],
      "published": "2025-05-27",
      "arxiv_url": "http://arxiv.org/abs/2505.20861v1",
      "pdf_url": "https://arxiv.org/pdf/2505.20861v1",
      "page": 7,
      "image_index": 10,
      "file_size": 32645,
      "format": "jpeg"
    },
    {
      "filename": "2505_20861v1_p7_img11.jpeg",
      "arxiv_id": "2505.20861v1",
      "title": "Exploring Timeline Control for Facial Motion Generation",
      "authors": [
        "Yifeng Ma",
        "Jinwei Qi",
        "Chaonan Ji"
      ],
      "published": "2025-05-27",
      "arxiv_url": "http://arxiv.org/abs/2505.20861v1",
      "pdf_url": "https://arxiv.org/pdf/2505.20861v1",
      "page": 7,
      "image_index": 11,
      "file_size": 32163,
      "format": "jpeg"
    },
    {
      "filename": "2505_20861v1_p7_img12.jpeg",
      "arxiv_id": "2505.20861v1",
      "title": "Exploring Timeline Control for Facial Motion Generation",
      "authors": [
        "Yifeng Ma",
        "Jinwei Qi",
        "Chaonan Ji"
      ],
      "published": "2025-05-27",
      "arxiv_url": "http://arxiv.org/abs/2505.20861v1",
      "pdf_url": "https://arxiv.org/pdf/2505.20861v1",
      "page": 7,
      "image_index": 12,
      "file_size": 39469,
      "format": "jpeg"
    },
    {
      "filename": "2505_20861v1_p7_img13.jpeg",
      "arxiv_id": "2505.20861v1",
      "title": "Exploring Timeline Control for Facial Motion Generation",
      "authors": [
        "Yifeng Ma",
        "Jinwei Qi",
        "Chaonan Ji"
      ],
      "published": "2025-05-27",
      "arxiv_url": "http://arxiv.org/abs/2505.20861v1",
      "pdf_url": "https://arxiv.org/pdf/2505.20861v1",
      "page": 7,
      "image_index": 13,
      "file_size": 37159,
      "format": "jpeg"
    },
    {
      "filename": "2505_20861v1_p7_img14.jpeg",
      "arxiv_id": "2505.20861v1",
      "title": "Exploring Timeline Control for Facial Motion Generation",
      "authors": [
        "Yifeng Ma",
        "Jinwei Qi",
        "Chaonan Ji"
      ],
      "published": "2025-05-27",
      "arxiv_url": "http://arxiv.org/abs/2505.20861v1",
      "pdf_url": "https://arxiv.org/pdf/2505.20861v1",
      "page": 7,
      "image_index": 14,
      "file_size": 39651,
      "format": "jpeg"
    },
    {
      "filename": "2505_20861v1_p7_img15.jpeg",
      "arxiv_id": "2505.20861v1",
      "title": "Exploring Timeline Control for Facial Motion Generation",
      "authors": [
        "Yifeng Ma",
        "Jinwei Qi",
        "Chaonan Ji"
      ],
      "published": "2025-05-27",
      "arxiv_url": "http://arxiv.org/abs/2505.20861v1",
      "pdf_url": "https://arxiv.org/pdf/2505.20861v1",
      "page": 7,
      "image_index": 15,
      "file_size": 36865,
      "format": "jpeg"
    },
    {
      "filename": "2505_20861v1_p7_img16.jpeg",
      "arxiv_id": "2505.20861v1",
      "title": "Exploring Timeline Control for Facial Motion Generation",
      "authors": [
        "Yifeng Ma",
        "Jinwei Qi",
        "Chaonan Ji"
      ],
      "published": "2025-05-27",
      "arxiv_url": "http://arxiv.org/abs/2505.20861v1",
      "pdf_url": "https://arxiv.org/pdf/2505.20861v1",
      "page": 7,
      "image_index": 16,
      "file_size": 35163,
      "format": "jpeg"
    },
    {
      "filename": "2505_20861v1_p7_img17.jpeg",
      "arxiv_id": "2505.20861v1",
      "title": "Exploring Timeline Control for Facial Motion Generation",
      "authors": [
        "Yifeng Ma",
        "Jinwei Qi",
        "Chaonan Ji"
      ],
      "published": "2025-05-27",
      "arxiv_url": "http://arxiv.org/abs/2505.20861v1",
      "pdf_url": "https://arxiv.org/pdf/2505.20861v1",
      "page": 7,
      "image_index": 17,
      "file_size": 40546,
      "format": "jpeg"
    },
    {
      "filename": "2505_20861v1_p7_img18.png",
      "arxiv_id": "2505.20861v1",
      "title": "Exploring Timeline Control for Facial Motion Generation",
      "authors": [
        "Yifeng Ma",
        "Jinwei Qi",
        "Chaonan Ji"
      ],
      "published": "2025-05-27",
      "arxiv_url": "http://arxiv.org/abs/2505.20861v1",
      "pdf_url": "https://arxiv.org/pdf/2505.20861v1",
      "page": 7,
      "image_index": 18,
      "file_size": 25053,
      "format": "png"
    },
    {
      "filename": "2505_20861v1_p7_img19.jpeg",
      "arxiv_id": "2505.20861v1",
      "title": "Exploring Timeline Control for Facial Motion Generation",
      "authors": [
        "Yifeng Ma",
        "Jinwei Qi",
        "Chaonan Ji"
      ],
      "published": "2025-05-27",
      "arxiv_url": "http://arxiv.org/abs/2505.20861v1",
      "pdf_url": "https://arxiv.org/pdf/2505.20861v1",
      "page": 7,
      "image_index": 19,
      "file_size": 38490,
      "format": "jpeg"
    },
    {
      "filename": "2505_20861v1_p7_img20.jpeg",
      "arxiv_id": "2505.20861v1",
      "title": "Exploring Timeline Control for Facial Motion Generation",
      "authors": [
        "Yifeng Ma",
        "Jinwei Qi",
        "Chaonan Ji"
      ],
      "published": "2025-05-27",
      "arxiv_url": "http://arxiv.org/abs/2505.20861v1",
      "pdf_url": "https://arxiv.org/pdf/2505.20861v1",
      "page": 7,
      "image_index": 20,
      "file_size": 40074,
      "format": "jpeg"
    },
    {
      "filename": "2505_20861v1_p7_img21.jpeg",
      "arxiv_id": "2505.20861v1",
      "title": "Exploring Timeline Control for Facial Motion Generation",
      "authors": [
        "Yifeng Ma",
        "Jinwei Qi",
        "Chaonan Ji"
      ],
      "published": "2025-05-27",
      "arxiv_url": "http://arxiv.org/abs/2505.20861v1",
      "pdf_url": "https://arxiv.org/pdf/2505.20861v1",
      "page": 7,
      "image_index": 21,
      "file_size": 39266,
      "format": "jpeg"
    },
    {
      "filename": "2505_20861v1_p7_img22.jpeg",
      "arxiv_id": "2505.20861v1",
      "title": "Exploring Timeline Control for Facial Motion Generation",
      "authors": [
        "Yifeng Ma",
        "Jinwei Qi",
        "Chaonan Ji"
      ],
      "published": "2025-05-27",
      "arxiv_url": "http://arxiv.org/abs/2505.20861v1",
      "pdf_url": "https://arxiv.org/pdf/2505.20861v1",
      "page": 7,
      "image_index": 22,
      "file_size": 37060,
      "format": "jpeg"
    },
    {
      "filename": "2505_20861v1_p7_img23.jpeg",
      "arxiv_id": "2505.20861v1",
      "title": "Exploring Timeline Control for Facial Motion Generation",
      "authors": [
        "Yifeng Ma",
        "Jinwei Qi",
        "Chaonan Ji"
      ],
      "published": "2025-05-27",
      "arxiv_url": "http://arxiv.org/abs/2505.20861v1",
      "pdf_url": "https://arxiv.org/pdf/2505.20861v1",
      "page": 7,
      "image_index": 23,
      "file_size": 37143,
      "format": "jpeg"
    },
    {
      "filename": "2505_20861v1_p8_img1.png",
      "arxiv_id": "2505.20861v1",
      "title": "Exploring Timeline Control for Facial Motion Generation",
      "authors": [
        "Yifeng Ma",
        "Jinwei Qi",
        "Chaonan Ji"
      ],
      "published": "2025-05-27",
      "arxiv_url": "http://arxiv.org/abs/2505.20861v1",
      "pdf_url": "https://arxiv.org/pdf/2505.20861v1",
      "page": 8,
      "image_index": 1,
      "file_size": 67443,
      "format": "png"
    },
    {
      "filename": "2505_20861v1_p8_img2.jpeg",
      "arxiv_id": "2505.20861v1",
      "title": "Exploring Timeline Control for Facial Motion Generation",
      "authors": [
        "Yifeng Ma",
        "Jinwei Qi",
        "Chaonan Ji"
      ],
      "published": "2025-05-27",
      "arxiv_url": "http://arxiv.org/abs/2505.20861v1",
      "pdf_url": "https://arxiv.org/pdf/2505.20861v1",
      "page": 8,
      "image_index": 2,
      "file_size": 23555,
      "format": "jpeg"
    },
    {
      "filename": "2505_20861v1_p8_img3.png",
      "arxiv_id": "2505.20861v1",
      "title": "Exploring Timeline Control for Facial Motion Generation",
      "authors": [
        "Yifeng Ma",
        "Jinwei Qi",
        "Chaonan Ji"
      ],
      "published": "2025-05-27",
      "arxiv_url": "http://arxiv.org/abs/2505.20861v1",
      "pdf_url": "https://arxiv.org/pdf/2505.20861v1",
      "page": 8,
      "image_index": 3,
      "file_size": 12646,
      "format": "png"
    },
    {
      "filename": "2505_20861v1_p8_img4.jpeg",
      "arxiv_id": "2505.20861v1",
      "title": "Exploring Timeline Control for Facial Motion Generation",
      "authors": [
        "Yifeng Ma",
        "Jinwei Qi",
        "Chaonan Ji"
      ],
      "published": "2025-05-27",
      "arxiv_url": "http://arxiv.org/abs/2505.20861v1",
      "pdf_url": "https://arxiv.org/pdf/2505.20861v1",
      "page": 8,
      "image_index": 4,
      "file_size": 29886,
      "format": "jpeg"
    },
    {
      "filename": "2505_20861v1_p8_img5.jpeg",
      "arxiv_id": "2505.20861v1",
      "title": "Exploring Timeline Control for Facial Motion Generation",
      "authors": [
        "Yifeng Ma",
        "Jinwei Qi",
        "Chaonan Ji"
      ],
      "published": "2025-05-27",
      "arxiv_url": "http://arxiv.org/abs/2505.20861v1",
      "pdf_url": "https://arxiv.org/pdf/2505.20861v1",
      "page": 8,
      "image_index": 5,
      "file_size": 29093,
      "format": "jpeg"
    }
  ]
}